fasal_logger/__init__.py
fasal_logger/_logger.py
logger.yml
fasal_logger-0.0.4.dist-info/WHEEL
fasal_logger-0.0.4.dist-info/METADATA
fasal_logger-0.0.4.dist-info/RECORD
