Metadata-Version: 2.1
Name: fasal-logger
Version: 0.0.4
Summary: json based python logger with support for slack notification
Author: Binay Pradhan
Author-email: binay.pradhan@wolkus.com
Requires-Python: >=3.7,<4.0
Classifier: Programming Language :: Python :: 3
Classifier: Programming Language :: Python :: 3.7
Classifier: Programming Language :: Python :: 3.8
Classifier: Programming Language :: Python :: 3.9
Classifier: Programming Language :: Python :: 3.10
Requires-Dist: PyYAML (==6.0)
Requires-Dist: ecs-logging (==2.0.0)
Requires-Dist: slack-sdk (==3.18.1)
